cc/__init__.py
cc/__main__.py
cc/agent.py
cc/alias.py
cc/cc_md.py
cc/cli.py
cc/commands/__init__.py
cc/commands/context.py
cc/commands/profile.py
cc/commands/session.py
cc/config.py
cc/conversations.py
cc/lib/__init__.py
cc/lib/fs.py
cc/lib/sqlite.py
cc/llms/__init__.py
cc/llms/glm.py
cc/render/__init__.py
cc/render/buffer.py
cc/render/color.py
cc/render/diff.py
cc/render/format.py
cc/render/renderer.py
cc/render/shell.py
cc/render/state.py
cogency_cc-0.1.0.dist-info/METADATA
cogency_cc-0.1.0.dist-info/WHEEL
cogency_cc-0.1.0.dist-info/entry_points.txt
cogency_cc-0.1.0.dist-info/RECORD
