Metadata-Version: 2.3
Name: cogency-cc
Version: 0.1.0
Summary: Streaming coding CLI for cogency agents.
License: Apache-2.0
Keywords: ai,agents,cli,terminal,cogency
Author: Tyson Chan
Author-email: tyson.chan@proton.me
Requires-Python: >=3.11,<4.0
Classifier: Development Status :: 3 - Alpha
Classifier: Intended Audience :: Developers
Classifier: License :: OSI Approved :: Apache Software License
Classifier: Programming Language :: Python :: 3
Classifier: Programming Language :: Python :: 3.11
Classifier: Programming Language :: Python :: 3.12
Classifier: Programming Language :: Python :: 3.13
Classifier: Topic :: Scientific/Engineering :: Artificial Intelligence
Classifier: Topic :: Software Development :: Libraries :: Python Modules
Classifier: Topic :: Terminals
Requires-Dist: aiohttp (>=3.9.0,<4.0.0)
Requires-Dist: cogency (>=3.2.0,<4.0.0)
Requires-Dist: typer (>=0.17.4,<0.18.0)
Project-URL: Homepage, https://github.com/iteebz/cogency-cc
Project-URL: Repository, https://github.com/iteebz/cogency-cc
